{
  "plugins": [
    "advanced-emoji",
    "splitter",
    "collapsible-chapters",
    "edit-link",
    "jsfiddle",
    "copy-code-button"
  ],
  "pluginsConfig": {
    "collapsible-chapters": {},
    "edit-link": {
      "base": "https://github.com/raulfdm/annotation-book/tree/master/",
      "label": "Edit This Page"
    },
    "jsfiddle": {
      "type": "script",
      "tabs": ["result", "js", "css", "html"],
      "height": "800",
      "width": "500",
      "fontColor": "0984e3"
    }
  }
}
